b64_cli-0.0.3.dist-info/DESCRIPTION.rst
b64_cli-0.0.3.dist-info/metadata.json
b64_cli-0.0.3.dist-info/top_level.txt
b64_cli-0.0.3.dist-info/METADATA
b64_cli-0.0.3.dist-info/WHEEL
b64_cli-0.0.3.dist-info/entry_points.txt
b64_cli-0.0.3.dist-info/RECORD
b64/__init__.py
b64/b64.py
b64/__main__.py
