Metadata-Version: 2.0
Name: b64-cli
Version: 0.0.3
Summary: A command line application to parse Base64 values
Home-page: https://github.com/RailRunner16/b64_cli
Author: Landon Gravat
Author-email: railinator4903@gmail.com
License: UNKNOWN
Platform: UNKNOWN
Classifier: Programming Language :: Python :: 3
Classifier: License :: OSI Approved :: MIT License
Classifier: Operating System :: OS Independent
